{
  "metadata": {
    "memo_id": "dm-2025-07-20topsoil-20management",
    "source_pdf": "references/memos/raw/DM%2025-07%20Topsoil%20Management.pdf",
    "checksum": "9118d351cd7ee17c83674017a8437ab35ae49a6cd9a43291d7002dc947d86d01",
    "extracted_at": "2025-10-16T17:24:22-0600",
    "character_count": "5106",
    "title": "Design Memo No. 25-07",
    "effective_date": "September 1, 2025"
  },
  "highlights": {
    "pay_items": [
      "000149",
      "000150",
      "06545",
      "12029",
      "2025"
    ],
    "spec_sections": [],
    "dollar_amounts": [
      "1.",
      "2.00",
      "2.22"
    ],
    "keywords_present": [
      "pay item",
      "unit price",
      "change"
    ]
  },
  "snippets": [
    "ce of Termination (NOT). \nRSP 629 -R-791, Topsoil Management , modifies the soil stripping requirement toward salvaging \nsuitable material for v egetation growth.  It includes two pay items: T opsoil Amendment Budget \nand Topsoil  Processing and Distribution. The provision will appear on the May  RSP menu.  \nThis memo includes:  \n\u2022 Design guidance for when t",
    "amendment budget and is a \ncompetitive ly bid item. It should be quantified by using the total area of revegetation  \n(permanent seeding and sodding ). For estimating purposes, a unit price of $2.22 per SYS may \nbe use d until a bid history is established.   \n Pay Item  Description  Unit  Notes  \n629-12029  Plant Growth Layer  SYS Until the sunset date, use",
    "\u2022 Topsoil  pay item  should not be included in the estimate.  \n \nIndiana Design Manual  Revisions  \nThe referenced sections of IDM  Chapter 17  have been revised to reflect the changes  to fertilizer \nrequirements . Section 17 -4.10(09)  Topsoil Management  has been added. \n \nQuestions  \nFor questions related to this design memo , please contact the Const",
    "629-000149  Topsoil Processing and Distribution  SYS",
    "629-000150  Topsoil Amendment Budget  DOL",
    "lettings,  the 621- 06545 Fertilizer pay item description will be revised  to Fertilizer for",
    "629-12029  Plant Growth Layer  SYS Until the sunset date, use RSP 629-R-630",
    "Page | 1 of 3  February 13 , 2025"
  ]
}